sqlilliput/__init__.py
sqlilliput/sqlite.py
sqlilliput-0.3.dist-info/LICENSE
sqlilliput-0.3.dist-info/METADATA
sqlilliput-0.3.dist-info/WHEEL
sqlilliput-0.3.dist-info/top_level.txt
sqlilliput-0.3.dist-info/RECORD
