Metadata-Version: 2.1
Name: sqlilliput
Version: 0.3
Summary: Python abstraction layer for SQLite3
Home-page: https://github.com/DinoSourceDK/sqlilliput
Author: DinoSource ApS
Author-email: info@dinosource.co
License: Apache
License-File: LICENSE
Requires-Dist: typing
